configilm/ConfigILM.py
configilm/Fusion/AbstractFusion.py
configilm/Fusion/BlockFusion.py
configilm/Fusion/BlockTuckerFusion.py
configilm/Fusion/ConcatMLPFusion.py
configilm/Fusion/LinearSumFusion.py
configilm/Fusion/MFBFusion.py
configilm/Fusion/MFHFusion.py
configilm/Fusion/MIDFusion.py
configilm/Fusion/MLBFusion.py
configilm/Fusion/MutanFusion.py
configilm/Fusion/TuckerFusion.py
configilm/Fusion/__init__.py
configilm/Fusion/blocks.py
configilm/__init__.py
configilm/extra/BENv1_utils.py
configilm/extra/BENv2_utils.py
configilm/extra/CustomTorchClasses.py
configilm/extra/DataModules/BENv1_DataModule.py
configilm/extra/DataModules/BENv2_DataModule.py
configilm/extra/DataModules/COCOQA_DataModule.py
configilm/extra/DataModules/ClassificationVQADataModule.py
configilm/extra/DataModules/HRVQA_DataModule.py
configilm/extra/DataModules/RSVQAHR_DataModule.py
configilm/extra/DataModules/RSVQALR_DataModule.py
configilm/extra/DataModules/RSVQAxBEN_DataModule.py
configilm/extra/DataModules/ThroughputTest_DataModule.py
configilm/extra/DataModules/__init__.py
configilm/extra/DataSets/BENv1_DataSet.py
configilm/extra/DataSets/BENv2_DataSet.py
configilm/extra/DataSets/COCOQA_DataSet.py
configilm/extra/DataSets/ClassificationVQADataset.py
configilm/extra/DataSets/HRVQA_DataSet.py
configilm/extra/DataSets/RSVQAHR_DataSet.py
configilm/extra/DataSets/RSVQALR_DataSet.py
configilm/extra/DataSets/RSVQAxBEN_DataSet.py
configilm/extra/DataSets/ThroughputTest_DataSet.py
configilm/extra/DataSets/__init__.py
configilm/extra/__init__.py
configilm/extra/_defaults.py
configilm/extra/data_dir.py
configilm/extra/huggingface_tokenizers/bert-base-uncased.tok/special_tokens_map.json
configilm/extra/huggingface_tokenizers/bert-base-uncased.tok/tokenizer_config.json
configilm/extra/huggingface_tokenizers/bert-base-uncased.tok/vocab.txt
configilm/extra/mock_data/.coverage
configilm/extra/mock_data/BENv1/BigEarthNetEncoded.lmdb/data.mdb
configilm/extra/mock_data/BENv1/BigEarthNetEncoded.lmdb/lock.mdb
configilm-0.7.1.dist-info/LICENSE
configilm-0.7.1.dist-info/METADATA
configilm-0.7.1.dist-info/WHEEL
configilm-0.7.1.dist-info/RECORD
