Metadata-Version: 2.3
Name: configilm
Version: 0.7.1
Summary: A state-of-the-art tool for Python developers seeking to rapidly and iteratively develop vision and language models within the [`pytorch`](https://pytorch.org/) framework
Author: Leonard Hackel
Author-email: l.hackel@tu-berlin.de
Requires-Python: >=3.9,<3.12
Classifier: Programming Language :: Python :: 3
Classifier: Programming Language :: Python :: 3.9
Classifier: Programming Language :: Python :: 3.10
Classifier: Programming Language :: Python :: 3.11
Provides-Extra: bigearthnet
Provides-Extra: full
Provides-Extra: full-lightning
Provides-Extra: full-pytorch-lightning
Requires-Dist: appdirs (>=1.4.4,<2.0.0)
Requires-Dist: bigearthnet-encoder (>=0.3.0,<0.4.0) ; extra == "bigearthnet" or extra == "full-pytorch-lightning" or extra == "full-lightning" or extra == "full"
Requires-Dist: lightning (>=2.0.0,<3.0.0) ; extra == "full-lightning" or extra == "full"
Requires-Dist: lmdb (>=1.4.0,<2.0.0) ; extra == "bigearthnet" or extra == "full-pytorch-lightning" or extra == "full-lightning" or extra == "full"
Requires-Dist: numpy (>=1.21.5,<2.0.0)
Requires-Dist: pyarrow (>=12.0.1,<13.0.0) ; extra == "bigearthnet" or extra == "full-pytorch-lightning" or extra == "full-lightning" or extra == "full"
Requires-Dist: pydantic (>=1.8,<2.0) ; extra == "bigearthnet" or extra == "full-pytorch-lightning" or extra == "full-lightning" or extra == "full"
Requires-Dist: pytorch-lightning (>=2.0.0,<3.0.0) ; extra == "full-pytorch-lightning"
Requires-Dist: timm (>=1.0,<2.0)
Requires-Dist: torch (>=2.0.0,!=2.0.1,!=2.1.0)
Requires-Dist: transformers (>=4.26.0,<5.0.0)
Project-URL: Documentation, https://lhackel-tub.github.io/ConfigILM/
Project-URL: Repository, https://github.com/lhackel-tub/ConfigILM
